plates/__init__.py
plates/__main__.py
plates/core.py
plates/data.json
plates/py.typed
plates-1.1.0.dist-info/LICENSE
plates-1.1.0.dist-info/METADATA
plates-1.1.0.dist-info/WHEEL
plates-1.1.0.dist-info/top_level.txt
plates-1.1.0.dist-info/RECORD
