Metadata-Version: 2.1
Name: plates
Version: 1.1.0
Summary: A module to operate with license plates and its patterns
Home-page: https://github.com/BatiDyDx/LicensePlatesToolbox
Author: Bautista Peirone
Author-email: bautista.peirone@gmail.com
License: Boost Software License 1.0 (BSL-1.0)
Project-URL: Source, https://github.com/BatiDyDx/LicensePlatesToolbox
Keywords: license plates,plates,utilities
Platform: unix
Platform: linux
Platform: osx
Platform: win32
Classifier: Programming Language :: Python :: 3
Classifier: Programming Language :: Python :: 3 :: Only
Classifier: Programming Language :: Python :: 3.6
Classifier: Programming Language :: Python :: 3.7
Classifier: Programming Language :: Python :: 3.8
Classifier: Programming Language :: Python :: 3.9
Classifier: Intended Audience :: Developers
Classifier: License :: OSI Approved :: Boost Software License 1.0 (BSL-1.0)
Classifier: Operating System :: OS Independent
Classifier: Typing :: Typed
Classifier: Topic :: Utilities
Requires-Python: >=3.6
License-File: LICENSE
Requires-Dist: rich (>=9)
Provides-Extra: test
Requires-Dist: mypy (>=0.910) ; extra == 'test'
Requires-Dist: pytest (>=6.2) ; extra == 'test'
Requires-Dist: tox (>=3.24) ; extra == 'test'
Requires-Dist: flake8 (>=4.0) ; extra == 'test'
